yamltool/__init__.py
yamltool/__main__.py
yamltool-0.1.2.dist-info/LICENSE.txt
yamltool-0.1.2.dist-info/METADATA
yamltool-0.1.2.dist-info/WHEEL
yamltool-0.1.2.dist-info/entry_points.txt
yamltool-0.1.2.dist-info/top_level.txt
yamltool-0.1.2.dist-info/RECORD
