Metadata-Version: 2.1
Name: yamltool
Version: 0.1.2
Summary: YAML tool, a clone of the json.tool Python module for YAML.
Home-page: https://git.shore.co.il/nimrod/yamltool
Author: Nimrod Adar
Author-email: nimrod@shore.co.il
License: MIT
Keywords: yaml,pre-commit
Platform: UNKNOWN
Classifier: Development Status :: 3 - Alpha
Classifier: Environment :: Console
Classifier: Intended Audience :: Developers
Classifier: Intended Audience :: Information Technology
Classifier: Intended Audience :: System Administrators
Classifier: License :: OSI Approved :: MIT License
Classifier: Programming Language :: Python :: 3
Classifier: Programming Language :: Python :: 3.6
Classifier: Programming Language :: Python :: 3.7
Classifier: Programming Language :: Python :: 3.8
Classifier: Programming Language :: Python :: 3.9
Classifier: Programming Language :: Python :: 3.10
Classifier: Topic :: Software Development
Classifier: Topic :: Software Development :: Debuggers
Classifier: Topic :: Software Development :: Quality Assurance
Classifier: Topic :: Text Processing :: Markup
Classifier: Topic :: Utilities
License-File: LICENSE.txt
Requires-Dist: ruamel.yaml (>=0.15.0)
